{
  "track": "情感赛道",
  "title": "真正毁掉婚姻的，不是吵架，而是不停翻旧账",
  "summary": "你知道吗，有时候压垮婚姻的，不是大吵大闹，而是那些悄无声息的“旧账重提”。就像温水煮青蛙，每次翻点小事，看似平静，其实心早就凉了。我见过太多夫妻，不吵不闹，却活得像陌生人，话还没说出口，就被一句“你上次也是这样”堵了回去。这种日子，比...",
  "word_count": 3403,
  "hot_topic": {
    "title": "真正毁掉婚姻的，不是吵架，而是不停翻旧账",
    "angle": "从日常沟通误区切入，解析情绪积压的伤害",
    "reason": "贴近普通人婚姻痛点，有共鸣且可正向引导，避免敏感，利于长期传播",
    "original_topic": "婚姻里,真正毁掉感情的,不是吵架,而是喋喋不休"
  },
  "ai_flavor_hits": [
    "综上所述"
  ],
  "ai_pattern_hits": [
    "排比三连结构",
    "否定对仗结构"
  ],
  "cover_image": "C:\\Users\\heroz\\Desktop\\wxarticle\\output\\2026-04-26\\情感赛道_2\\cover.jpg",
  "generated_at": "2026-04-26T17:15:11.795824"
}